{"chunk_definitions":[{"chunk_id":"c1pw05lzwofdp","chunk_label":"unnamed-chunk-1","document_id":null,"expansion_state":0,"options":{"engine":"r","label":"unnamed-chunk-1"},"row":71,"row_count":1,"visible":true},{"chunk_id":"c6x27xm9spvkb","chunk_label":"unnamed-chunk-2","document_id":null,"expansion_state":0,"options":{"engine":"r","label":"unnamed-chunk-6"},"row":110,"row_count":1,"visible":true},{"chunk_id":"csxypa6zteg4t","chunk_label":"unnamed-chunk-3","document_id":null,"expansion_state":0,"options":{"engine":"r","label":"unnamed-chunk-3"},"row":148,"row_count":1,"visible":true},{"chunk_id":"cyc4ru14hxcf2","chunk_label":"unnamed-chunk-4","document_id":null,"expansion_state":0,"options":{"engine":"r","label":"unnamed-chunk-4"},"row":179,"row_count":1,"visible":true},{"chunk_id":"czdgs2gcbce6u","chunk_label":"unnamed-chunk-5","document_id":null,"expansion_state":0,"options":{"engine":"r","label":"unnamed-chunk-9"},"row":195,"row_count":1,"visible":true},{"chunk_id":"cwlrlfkm0jw8t","chunk_label":"unnamed-chunk-6","document_id":null,"expansion_state":0,"options":{"engine":"r","label":"unnamed-chunk-10"},"row":249,"row_count":1,"visible":true}],"doc_write_time":1589682738}